debgpt/__init__.py
debgpt/arguments.py
debgpt/backend.py
debgpt/cache.py
debgpt/cli.py
debgpt/configurator.py
debgpt/defaults.py
debgpt/embeddings.py
debgpt/frontend.py
debgpt/llm.py
debgpt/mapreduce.py
debgpt/nm_templates.py
debgpt/policy.py
debgpt/reader.py
debgpt/replay.py
debgpt/retrieval.py
debgpt/vectordb.py
debgpt-0.7.8.dist-info/licenses/COPYING
debgpt-0.7.8.dist-info/licenses/COPYING.LESSER
debgpt-0.7.8.dist-info/METADATA
debgpt-0.7.8.dist-info/WHEEL
debgpt-0.7.8.dist-info/entry_points.txt
debgpt-0.7.8.dist-info/top_level.txt
debgpt-0.7.8.dist-info/RECORD
