Metadata-Version: 2.4
Name: debgpt
Version: 0.7.8
Summary: DebGPT -- General Purpose Terminal LLM Tool with Some Debian-Specific Design
Author-email: Mo Zhou <lumin@debian.org>
License: LGPL-3.0+
Project-URL: Homepage, https://salsa.debian.org/deeplearning-team/debgpt
Project-URL: Issues, https://salsa.debian.org/deeplearning-team/debgpt/-/issues
Classifier: Programming Language :: Python :: 3
Classifier: Operating System :: OS Independent
Requires-Python: >=3.10
License-File: COPYING
License-File: COPYING.LESSER
Requires-Dist: rich
Requires-Dist: prompt_toolkit
Requires-Dist: openai
Requires-Dist: requests
Requires-Dist: bs4
Requires-Dist: tomli
Requires-Dist: tenacity
Requires-Dist: pygments
Requires-Dist: urwid
Requires-Dist: lz4
Requires-Dist: numpy
Provides-Extra: dev
Requires-Dist: pyflakes; extra == "dev"
Requires-Dist: pylint; extra == "dev"
Requires-Dist: pypdf; extra == "dev"
Requires-Dist: pytest-cov; extra == "dev"
Requires-Dist: pytest-timeout; extra == "dev"
Requires-Dist: pytest-xdist; extra == "dev"
Requires-Dist: pytest>=7.0; extra == "dev"
Requires-Dist: anthropic; extra == "dev"
Requires-Dist: google-generativeai; extra == "dev"
Requires-Dist: pytorch; extra == "dev"
Requires-Dist: transformers; extra == "dev"
Dynamic: license-file
